ilpincometax/__init__.py
ilpincometax/taxcalc.py
ilpincometax-0.1.2.dist-info/WHEEL
ilpincometax-0.1.2.dist-info/METADATA
ilpincometax-0.1.2.dist-info/RECORD
