Metadata-Version: 2.1
Name: ilpincometax
Version: 0.1.2
Summary: library for calculating US federal tax for 2022, this is my personal project so do not recommend to use in production scenario with out testing
Author: iluvpython
Author-email: iluvpython@outlook.com
Requires-Python: >=3.1,<4.0
Classifier: Programming Language :: Python :: 3
Classifier: Programming Language :: Python :: 3.10
Classifier: Programming Language :: Python :: 3.4
Classifier: Programming Language :: Python :: 3.5
Classifier: Programming Language :: Python :: 3.6
Classifier: Programming Language :: Python :: 3.7
Classifier: Programming Language :: Python :: 3.8
Classifier: Programming Language :: Python :: 3.9
